cadence/api/CadenceHTTPClient.py
cadence/api/OneTimeToken.py
cadence/api/__init__.py
cadence/api/convert.py
cadence/api/exceptions.py
cadence/api/model/Execution.py
cadence/api/model/JetTrainConfig.py
cadence/api/model/License.py
cadence/api/model/Project.py
cadence/api/model/ProjectView.py
cadence/api/model/Provisioning.py
cadence/api/model/StartExecutionRequest.py
cadence/api/model/StorageKey.py
cadence/api/model/StorageType.py
cadence/api/model/TCLogInputStream.py
cadence/api/model/User.py
cadence/api/model/__init__.py
cadence/api/model/billing.py
cadence/api/model/common.py
cadence/api/model/connector.py
cadence/api/model/environment.py
cadence/api/model/logs.py
cadence/api/model/storage.py
cadence/api/sync.py
cadence/api/utils.py
cadence/cli/__init__.py
cadence/cli/__main__.py
cadence/cli/entrypoint.py
cadence/cli/execution.py
cadence/cli/impl.py
cadence/cli/login.py
cadence/cli/prompts/__init__.py
cadence/cli/prompts/storage.py
cadence/cli/storage.py
cadence/cli/utils.py
cadence/cli/workspace.py
cadence/resources/__init__.py
cadence/resources/login_success.html
cadence/utils/__init__.py
cadence/utils/config.py
cadence/utils/interpolation.py
cadence/utils/keyring.py
cadence/utils/storage.py
jetbrains_cadence-1.2.0.dist-info/METADATA
jetbrains_cadence-1.2.0.dist-info/WHEEL
jetbrains_cadence-1.2.0.dist-info/entry_points.txt
jetbrains_cadence-1.2.0.dist-info/RECORD
