Metadata-Version: 2.3
Name: jetbrains-cadence
Version: 1.2.0
Summary: JetBrains Cadence CLI
Author: Mikhail Meringov
Author-email: mikhail.meringov@jetbrains.com
Requires-Python: >=3.11
Classifier: Programming Language :: Python :: 3
Classifier: Programming Language :: Python :: 3.11
Classifier: Programming Language :: Python :: 3.12
Classifier: Programming Language :: Python :: 3.13
Requires-Dist: awscli (>=1.41.12,<2.0.0)
Requires-Dist: click (==8.2.1)
Requires-Dist: httpx (>=0.28.1,<0.29.0)
Requires-Dist: keyring (>=25.6.0,<26.0.0)
Requires-Dist: omegaconf (>=2.3.0,<3.0.0)
Requires-Dist: pydantic (>=2.11.7,<3.0.0)
Requires-Dist: pyyaml (>=6.0.2,<7.0.0)
